grey.py
grey-0.0.1.dist-info/METADATA
grey-0.0.1.dist-info/RECORD
grey-0.0.1.dist-info/WHEEL
grey-0.0.1.dist-info/entry_points.txt
grey-0.0.1.dist-info/top_level.txt
