Metadata-Version: 2.1
Name: grey
Version: 0.0.1
Summary: Grey, because I didn't like Black or White.
Home-page: https://github.com/skorokithakis/gray
Author: Stavros Korokithakis
Author-email: hi@stavros.io
License: MIT
Platform: UNKNOWN
Classifier: License :: OSI Approved :: MIT License
Classifier: Programming Language :: Python
Classifier: Programming Language :: Python :: 3
Classifier: Programming Language :: Python :: 3.6
Classifier: Programming Language :: Python :: Implementation :: CPython
Classifier: Programming Language :: Python :: Implementation :: PyPy
Requires-Python: >=3.6.0
Requires-Dist: black (>=18.5a0)
